rsich/__init__.py
rsich/rsich.py
rsich-0.0.2.dist-info/LICENSE.txt
rsich-0.0.2.dist-info/METADATA
rsich-0.0.2.dist-info/WHEEL
rsich-0.0.2.dist-info/top_level.txt
rsich-0.0.2.dist-info/RECORD
