Metadata-Version: 2.1
Name: rsich
Version: 0.0.2
Summary: python package to shortcut functions when scripting for RayStation
Home-page: https://github.com/isadorap/rsich
Author: Isadora Platoni
Author-email: isadora.platoni@nhs.net
Classifier: Programming Language :: Python :: 3
Classifier: License :: OSI Approved :: MIT License
Classifier: Operating System :: OS Independent
Requires-Python: >=3.7
License-File: LICENSE.txt
